h3spark/__init__.py
h3spark/convenience.py
h3spark/models.py
h3spark/native.py
h3spark/utils.py
h3spark-0.1.6.dist-info/METADATA
h3spark-0.1.6.dist-info/WHEEL
h3spark-0.1.6.dist-info/licenses/LICENSE
h3spark-0.1.6.dist-info/RECORD
