Metadata-Version: 2.4
Name: h3spark
Version: 0.1.6
Summary: Lightweight pyspark wrapper for h3-py
Author-email: Joseph Chotard <h3spark@chotard.com>
License: MIT License
License-File: LICENSE
Keywords: h3,h3-py,pyspark,spark
Classifier: License :: OSI Approved :: MIT License
Classifier: Operating System :: OS Independent
Classifier: Programming Language :: Python :: 3
Requires-Python: >=3.9
Requires-Dist: h3<4.3,>=4.1
Requires-Dist: pyspark<4.0,>=3.0
